leop/__init__.py
leop/algo.py
leop/classes.py
leop/index.py
leop/l_os.py
leop/remote.py
leop-0.1.8.dist-info/licenses/LICENSE
leop-0.1.8.dist-info/METADATA
leop-0.1.8.dist-info/WHEEL
leop-0.1.8.dist-info/top_level.txt
leop-0.1.8.dist-info/RECORD
