Metadata-Version: 2.4
Name: leop
Version: 0.1.8
Summary: leop
Author: Leo
Author-email: lindb2020@hotmail.com
License: MIT
Requires-Python: >=3.6
License-File: LICENSE
Requires-Dist: pywin32
Requires-Dist: pyautogui
Dynamic: author
Dynamic: author-email
Dynamic: description
Dynamic: description-content-type
Dynamic: license
Dynamic: license-file
Dynamic: requires-dist
Dynamic: requires-python
Dynamic: summary
